dataform_unit_testing/__init__.py
dataform_unit_testing/__main__.py
dataform_unit_testing/final_test_ctes.txt
dataform_unit_testing/sql_unit_test_builder.py
dataform_unit_testing/unit_test_extractor.py
dataform_unit_testing/unit_test_parser.py
dataform_unit_testing/unit_test_runner.py
dataform_unit_testing/__pycache__/__init__.cpython-311.pyc
dataform_unit_testing/__pycache__/sql_unit_test_builder.cpython-311.pyc
dataform_unit_testing/__pycache__/unit_test_extractor.cpython-311.pyc
dataform_unit_testing/__pycache__/unit_test_parser.cpython-311.pyc
dataform_unit_testing/__pycache__/unit_test_runner.cpython-311.pyc
dataform_unit_tests-1.3.0.dist-info/LICENSE
dataform_unit_tests-1.3.0.dist-info/METADATA
dataform_unit_tests-1.3.0.dist-info/WHEEL
dataform_unit_tests-1.3.0.dist-info/top_level.txt
dataform_unit_tests-1.3.0.dist-info/RECORD
