Metadata-Version: 2.2
Name: dataform-unit-tests
Version: 1.3.0
Summary: Code that is executed as part of GitHub Actions pipelines in Dataform-enabled Google Cloud projects to perform unit tests on Dataform models
Author: Neeraj Morar
License: Apache-2.0
Project-URL: Homepage, https://neerajmorar.wixsite.com/dataform-unit-tests
Requires-Python: >=3.10
License-File: LICENSE
Requires-Dist: google-cloud-dataform==0.5.13
Requires-Dist: google-cloud-bigquery==3.26.0
Requires-Dist: tabulate==0.9.0
Requires-Dist: pandas==2.2.3
Requires-Dist: jsonschema==4.23.0
